dtopia/__init__.py
dtopia/dtopia.py
dtopia-1.4.3.dist-info/METADATA
dtopia-1.4.3.dist-info/WHEEL
dtopia-1.4.3.dist-info/top_level.txt
dtopia-1.4.3.dist-info/RECORD
