Metadata-Version: 2.1
Name: dtopia
Version: 1.4.3
Summary: Dtopia Discord Tools
Author: Toxbic
Author-email: your@email.com
Requires-Dist: requests
Requires-Dist: websockets
Requires-Dist: colorama
